wikipron/__init__.py
wikipron/cli.py
wikipron/config.py
wikipron/languagecodes.py
wikipron/scrape.py
wikipron/typing.py
wikipron/extract/__init__.py
wikipron/extract/blt.py
wikipron/extract/cmn.py
wikipron/extract/core.py
wikipron/extract/default.py
wikipron/extract/jpn.py
wikipron/extract/khb.py
wikipron/extract/khm.py
wikipron/extract/lat.py
wikipron/extract/shn.py
wikipron/extract/tha.py
wikipron/extract/vie.py
wikipron/extract/yue.py
wikipron-1.3.3.dist-info/LICENSE.txt
wikipron-1.3.3.dist-info/METADATA
wikipron-1.3.3.dist-info/WHEEL
wikipron-1.3.3.dist-info/entry_points.txt
wikipron-1.3.3.dist-info/top_level.txt
wikipron-1.3.3.dist-info/RECORD
