Metadata-Version: 2.1
Name: wikipron
Version: 1.3.3
Summary: Scraping grapheme-to-phoneme data from Wiktionary
Author-email: WikiPron authors <kylebgorman@gmail.com>
License: Apache 2.0
Project-URL: Homepage, https://github.com/CUNY-CL/wikipron
Keywords: computational linguistics,natural language processing,phonology,phonetics,speech,language,Wiktionary
Classifier: Development Status :: 5 - Production/Stable
Classifier: License :: OSI Approved :: Apache Software License
Classifier: Operating System :: OS Independent
Classifier: Environment :: Console
Classifier: Programming Language :: Python :: 3
Classifier: Programming Language :: Python :: 3 :: Only
Classifier: Programming Language :: Python :: 3.8
Classifier: Programming Language :: Python :: 3.9
Classifier: Programming Language :: Python :: 3.10
Classifier: Programming Language :: Python :: 3.11
Classifier: Programming Language :: Python :: 3.12
Classifier: Topic :: Text Processing :: Linguistic
Requires-Python: >=3.8
License-File: LICENSE.txt
Requires-Dist: lxml-html-clean
Requires-Dist: python-iso639 >=2022.11.27
Requires-Dist: requests >=2.32.3
Requires-Dist: requests-html
Requires-Dist: segments <3,>=2.2.0
